FileTransfer/__init__.py
FileTransfer_LQR471814-0.1.2.dist-info/LICENSE
FileTransfer_LQR471814-0.1.2.dist-info/METADATA
FileTransfer_LQR471814-0.1.2.dist-info/WHEEL
FileTransfer_LQR471814-0.1.2.dist-info/top_level.txt
FileTransfer_LQR471814-0.1.2.dist-info/RECORD
