Metadata-Version: 2.1
Name: FileTransfer-LQR471814
Version: 0.1.2
Summary: A module that makes File Transfer a bit easier.
Home-page: https://github.com/LQR471814/FileTransfer
Author: LQR471814
Author-email: bramblefern1013@gmail.com
License: UNKNOWN
Platform: UNKNOWN
Classifier: Programming Language :: Python :: 3
Classifier: License :: OSI Approved :: MIT License
Classifier: Operating System :: OS Independent
Requires-Python: >=3.6
